vhh_cmc/CMC.py
vhh_cmc/Configuration.py
vhh_cmc/Evaluation.py
vhh_cmc/OpticalFlow.py
vhh_cmc/OpticalFlow_Dense.py
vhh_cmc/OpticalFlow_ORB.py
vhh_cmc/OpticalFlow_SIFT.py
vhh_cmc/PreProcessing.py
vhh_cmc/Video.py
vhh_cmc/Visualization.py
vhh_cmc/__init__.py
vhh_cmc/cmc_io.py
vhh_cmc-1.4.0.dist-info/LICENSE
vhh_cmc-1.4.0.dist-info/METADATA
vhh_cmc-1.4.0.dist-info/WHEEL
vhh_cmc-1.4.0.dist-info/top_level.txt
vhh_cmc-1.4.0.dist-info/RECORD
