Metadata-Version: 2.1
Name: vhh-cmc
Version: 1.4.0
Summary: Camera Movements Classification Package
Home-page: https://github.com/dahe-cvl/vhh_cmc
Author: Daniel Helm
Author-email: daniel.helm@tuwien.ac.at
License: UNKNOWN
Platform: UNKNOWN
License-File: LICENSE
Requires-Dist: PyYAML
Requires-Dist: pandas
Requires-Dist: NumPy
Requires-Dist: matplotlib
Requires-Dist: scipy
Requires-Dist: scikit-learn
Requires-Dist: Sphinx
Requires-Dist: sphinxcontrib-bibtex
Requires-Dist: sphinxcontrib-autoyaml
Requires-Dist: pymp-pypi
Requires-Dist: opencv-python
